novikovtv_parser_tenchat/__init__.py
novikovtv_parser_tenchat/parser/__init__.py
novikovtv_parser_tenchat/parser/main.py
novikovtv_parser_tenchat/parser/selenium_tenchat_parser/SeleniumTenchatParser.py
novikovtv_parser_tenchat/parser/selenium_tenchat_parser/__init__.py
novikovtv_parser_tenchat/util/__init__.py
novikovtv_parser_tenchat/util/env.py
novikovtv_parser_tenchat/util/singleton.py
novikovtv_parser_tenchat-1.0.6.dist-info/METADATA
novikovtv_parser_tenchat-1.0.6.dist-info/WHEEL
novikovtv_parser_tenchat-1.0.6.dist-info/licenses/LICENSE
novikovtv_parser_tenchat-1.0.6.dist-info/RECORD
