Metadata-Version: 2.4
Name: novikovtv-parser-tenchat
Version: 1.0.6
Summary: This is the TenChat search engine parser
Project-URL: Homepage, https://github.com/asianetsievskaya/parser-yandex
Author-email: Tsuedewn <kutner.co@gmail.com>
Maintainer-email: domster704 <domster704@mail.ru>
License-Expression: MIT
License-File: LICENSE
Classifier: License :: OSI Approved :: MIT License
Classifier: Operating System :: OS Independent
Classifier: Programming Language :: Python :: 3.11
Requires-Python: >=3.11
Requires-Dist: selenium==4.30.0
Requires-Dist: webdriver-manager==4.0.2
